oidcpy/__init__.py
oidcpy/authorize.py
oidcpy/crypto.py
oidcpy-0.0.5.dist-info/LICENSE
oidcpy-0.0.5.dist-info/METADATA
oidcpy-0.0.5.dist-info/WHEEL
oidcpy-0.0.5.dist-info/top_level.txt
oidcpy-0.0.5.dist-info/RECORD
