Metadata-Version: 2.1
Name: oidcpy
Version: 0.0.5
Summary: OpenID Connect library code
Home-page: https://github.com/marcelvandendungen/oidcpy
Author: Marcel van den Dungen
Author-email: author@example.com
License: UNKNOWN
Platform: UNKNOWN
Classifier: Programming Language :: Python :: 3
Classifier: License :: OSI Approved :: MIT License
Classifier: Operating System :: OS Independent
Requires-Python: >=3.6
